om/__init__.py
om/om.py
omak-0.1.0.dist-info/licenses/LICENSE
omak-0.1.0.dist-info/METADATA
omak-0.1.0.dist-info/WHEEL
omak-0.1.0.dist-info/top_level.txt
omak-0.1.0.dist-info/RECORD
