Metadata-Version: 2.4
Name: omak
Version: 0.1.0
Summary: Small collection of utility functions
Author-email: Zad Zack <zadzack409@gmail.com>
License: MIT
Classifier: Programming Language :: Python :: 3
Classifier: License :: OSI Approved :: MIT License
Classifier: Operating System :: OS Independent
Requires-Python: >=3.8
License-File: LICENSE
Dynamic: license-file
